{
    "key": "group_576960231da27",
    "title": "Story Fields",
    "fields": [
        {
            "key": "field_5a1f47113efe8",
            "label": "Feature Label",
            "name": "feature_label",
            "type": "select",
            "instructions": "",
            "required": 0,
            "conditional_logic": 0,
            "wrapper": {
                "width": "",
                "class": "",
                "id": ""
            },
            "choices": {
                "Signature Story": "Signature Story",
                "Video": "Video",
                "Dean's Letter": "Dean's Letter"
            },
            "default_value": [],
            "allow_null": 0,
            "multiple": 0,
            "ui": 0,
            "ajax": 0,
            "return_format": "value",
            "placeholder": ""
        },
        {
            "key": "field_537638937d170",
            "label": "Story Link (URL)",
            "name": "story_link_url",
            "type": "text",
            "instructions": "",
            "required": 0,
            "conditional_logic": 0,
            "wrapper": {
                "width": "",
                "class": "",
                "id": ""
            },
            "default_value": "",
            "placeholder": "e.g. http:\/\/seattletimes.com\/",
            "prepend": "",
            "append": "",
            "formatting": "html",
            "maxlength": "",
            "readonly": 0,
            "disabled": 0
        },
        {
            "key": "field_537638b87d171",
            "label": "Story Source Name",
            "name": "story_source_name",
            "type": "text",
            "instructions": "",
            "required": 0,
            "conditional_logic": 0,
            "wrapper": {
                "width": "",
                "class": "",
                "id": ""
            },
            "default_value": "Read more at UW Today",
            "placeholder": "",
            "prepend": "",
            "append": "",
            "formatting": "html",
            "maxlength": "",
            "readonly": 0,
            "disabled": 0
        }
    ],
    "location": [
        [
            {
                "param": "post_type",
                "operator": "==",
                "value": "post"
            }
        ]
    ],
    "menu_order": 0,
    "position": "side",
    "style": "default",
    "label_placement": "top",
    "instruction_placement": "label",
    "hide_on_screen": "",
    "active": 1,
    "description": "",
    "modified": 1511999697
}